{
    "hotel_id": "h001",
    "slug": "seaside-haven",
    "images": [
      "/uploads/h001/1732444678882-hotel1.jpeg",
      "/uploads/h001/1732083442754-hotel3.jpeg",
      "/uploads/h001/1732272405149-hotel7.jpeg",
      "/uploads/h001/1732363145873-hotel8.jpeg",
      "/uploads/h001/1732418913395-hotel9.jpeg",
      "/uploads/h001/1732293909504-hotel10.jpeg"
    ],
    "title": "Seaside Haven",
    "description": "A beautiful beachfront hotel with stunning views and modern amenities.",
    "guest_count": 6,
    "bedroom_count": 3,
    "bathroom_count": 2,
    "amenities": [
      "Free WiFi",
      "Pool",
      "Air Conditioning",
      "Breakfast Included"
    ],
    "host_information": {
      "name": "John Doe",
      "contact": "+123456789",
      "email": "john@example.com"
    },
    "address": "123 Ocean Drive, Miami Beach, FL",
    "latitude": 25.790654,
    "longitude": -80.1300455,
    "rooms": [
      {
        "hotel_slug": "seaside-haven",
        "room_slug": "ocean-view-suite",
        "room_image": "https://example.com/hotel1/room1.jpg",
        "room_title": "Ocean View Suite",
        "bedroom_count": 1
      }